condeltri.cpython-310-darwin.so
condeltri-0.0.3.dist-info/RECORD
condeltri-0.0.3.dist-info/WHEEL
condeltri-0.0.3.dist-info/METADATA
condeltri-0.0.3.dist-info/licenses/LICENSE
