Metadata-Version: 2.2
Name: condeltri
Version: 0.0.3
Summary: Constrained Delaunay Triangulation
Author: Leica Geosystems
License: MPL-2.0
Project-URL: Repository, https://github.com/mdealencar/PythonCDT/tree/ConDelTri
Requires-Python: >=3.10
